{
    "Animal furs": {
        "id": "49446"
    },
    "Fossilised bone": {
        "id": "49448"
    },
    "Goldrune": {
        "id": "49450"
    },
    "Leather scraps": {
        "id": "49452"
    },
    "Orthenglass": {
        "id": "49454"
    },
    "Samite silk": {
        "id": "49456"
    },
    "Soapstone": {
        "id": "49458"
    },
    "Third Age iron": {
        "id": "49460"
    },
    "Vellum": {
        "id": "49462"
    },
    "White oak": {
        "id": "49464"
    },
    "Aetherium alloy": {
        "id": "49466"
    },
    "Armadylean yellow": {
        "id": "49468"
    },
    "Quintessence": {
        "id": "49470"
    },
    "Stormguard steel": {
        "id": "49472"
    },
    "Wings of War": {
        "id": "49474"
    },
    "Malachite green": {
        "id": "49476"
    },
    "Mark of the Kyzaj": {
        "id": "49478"
    },
    "Vulcanised rubber": {
        "id": "49480"
    },
    "Warforged bronze": {
        "id": "49482"
    },
    "Yu'biusk clay": {
        "id": "49484"
    },
    "Cobalt blue": {
        "id": "49486"
    },
    "Everlight silvthril": {
        "id": "49488"
    },
    "Keramos": {
        "id": "49490"
    },
    "Star of Saradomin": {
        "id": "49492"
    },
    "White marble": {
        "id": "49494"
    },
    "Cadmium red": {
        "id": "49496"
    },
    "Chaotic brimstone": {
        "id": "49498"
    },
    "Demonhide": {
        "id": "49500"
    },
    "Eye of Dagon": {
        "id": "49502"
    },
    "Hellfire metal": {
        "id": "49504"
    },
    "Ancient vis": {
        "id": "49506"
    },
    "Blood of Orcus": {
        "id": "49508"
    },
    "Imperial steel": {
        "id": "49510"
    },
    "Tyrian purple": {
        "id": "49512"
    },
    "Zarosian insignia": {
        "id": "49514"
    },
    "Carbon black": {
        "id": "50686"
    },
    "Compass rose": {
        "id": "50688"
    },
    "Dragon metal": {
        "id": "50690"
    },
    "Felt": {
        "id": "50692"
    },
    "Orgone": {
        "id": "50694"
    }
}

